{
  "project_info": {
    "project_number": "818835540581",
    "project_id": "notification-app-565cf",
    "storage_bucket": "notification-app-565cf.appspot.com"
  },
  "client": [
    {
      "client_info": {
        "mobilesdk_app_id": "1:818835540581:android:d855edda83f9e15bce948c",
        "android_client_info": {
          "package_name": "com.example.notification_app"
        }
      },
      "oauth_client": [
        {
          "client_id": "818835540581-5cfrvbpdvohiuo9htb7m1v7ai6moqg87.apps.googleusercontent.com",
          "client_type": 3
        }
      ],
      "api_key": [
        {
          "current_key": "AIzaSyA0esEPEQmfEC0pdzZ4tSbPJytjj1UAqRY"
        }
      ],
      "services": {
        "appinvite_service": {
          "other_platform_oauth_client": [
            {
              "client_id": "818835540581-5cfrvbpdvohiuo9htb7m1v7ai6moqg87.apps.googleusercontent.com",
              "client_type": 3
            }
          ]
        }
      }
    }
  ],
  "configuration_version": "1"
}